fast_dp/__init__.py
fast_dp/autoindex.py
fast_dp/cell_spacegroup.py
fast_dp/diff.py
fast_dp/fast_dp.py
fast_dp/fast_rdp.py
fast_dp/image_names.py
fast_dp/image_readers.py
fast_dp/integrate.py
fast_dp/logger.py
fast_dp/merge.py
fast_dp/output.py
fast_dp/pointgroup.py
fast_dp/pointless_reader.py
fast_dp/run_job.py
fast_dp/scale.py
fast_dp/xds_reader.py
fast_dp/templates/ispyb.xml
fast_dp-1.7.dist-info/LICENSE
fast_dp-1.7.dist-info/METADATA
fast_dp-1.7.dist-info/WHEEL
fast_dp-1.7.dist-info/entry_points.txt
fast_dp-1.7.dist-info/top_level.txt
fast_dp-1.7.dist-info/RECORD
