Metadata-Version: 2.1
Name: fast_dp
Version: 1.7
Summary: Fast DP: Fast Data Processsing with XDS
Author-email: Diamond Light Source <scientificsoftware@diamond.ac.uk>
License: Apache-2.0
Project-URL: Homepage, https://github.com/DiamondLightSource/fast_dp
Project-URL: Downloads, https://github.com/DiamondLightSource/fast_dp/releases
Classifier: Development Status :: 5 - Production/Stable
Classifier: Programming Language :: Python :: 3.9
Classifier: Programming Language :: Python :: 3.10
Classifier: Programming Language :: Python :: 3.11
Classifier: Operating System :: POSIX :: Linux
Requires-Python: >=3.9
License-File: LICENSE
Requires-Dist: procrunner
